visu_hlo.py
visu_hlo-0.1.dist-info/METADATA
visu_hlo-0.1.dist-info/WHEEL
visu_hlo-0.1.dist-info/licenses/LICENSE
visu_hlo-0.1.dist-info/RECORD
