Metadata-Version: 2.4
Name: visu-hlo
Version: 0.1
Summary: Displays the HLO representation of (un-)jitted functions as SVG
Project-URL: repository, https://github.com/CMBSciPol/visu_hlo
Author-email: Pierre Chanial <chanial@apc.in2p3.fr>
License-Expression: MIT
License-File: LICENSE
Classifier: Intended Audience :: Education
Classifier: Intended Audience :: Science/Research
Classifier: Programming Language :: Python :: 3.10
Classifier: Programming Language :: Python :: 3.11
Classifier: Programming Language :: Python :: 3.12
Classifier: Programming Language :: Python :: 3.13
Classifier: Topic :: Scientific/Engineering :: Mathematics
Classifier: Topic :: Scientific/Engineering :: Visualization
Classifier: Topic :: Software Development :: Debuggers
Requires-Python: >=3.10
Requires-Dist: graphviz>=0.18.2
Requires-Dist: jax>=0.4.0
Requires-Dist: jaxlib>=0.4.0
